mevis/__init__.py
mevis/_internal/__init__.py
mevis/_internal/args.py
mevis/_internal/cli.py
mevis/_internal/conversion.py
mevis/_internal/filtering.py
mevis/_internal/inspection.py
mevis/_internal/io.py
mevis/_internal/layouting.py
mevis/_internal/plotting.py
mevis-0.1.1.dist-info/LICENSE
mevis-0.1.1.dist-info/METADATA
mevis-0.1.1.dist-info/WHEEL
mevis-0.1.1.dist-info/entry_points.txt
mevis-0.1.1.dist-info/top_level.txt
mevis-0.1.1.dist-info/RECORD
