Metadata-Version: 2.1
Name: mevis
Version: 0.1.1
Summary: Interactive metagraph visualizations with Python and HTML/CSS/JS for OpenCog.
Home-page: https://robert-haas.github.io/mevis-docs/
Author: Robert Haas
Author-email: robert.haas@protonmail.com
License: Apache License, Version 2.0
Platform: UNKNOWN
Classifier: Development Status :: 3 - Alpha
Classifier: Intended Audience :: Developers
Classifier: Intended Audience :: Education
Classifier: Intended Audience :: Science/Research
Classifier: License :: OSI Approved :: Apache Software License
Classifier: Natural Language :: English
Classifier: Operating System :: OS Independent
Classifier: Programming Language :: Python :: 3
Classifier: Topic :: Multimedia :: Graphics
Classifier: Topic :: Multimedia :: Graphics :: Presentation
Classifier: Topic :: Scientific/Engineering
Classifier: Topic :: Scientific/Engineering :: Visualization
Requires-Python: >=3.5
License-File: LICENSE
Requires-Dist: gravis
Requires-Dist: networkx (>2<3)
Requires-Dist: numpy (>1.15<2)
Requires-Dist: setuptools (>=40.0)
